acex/api/api/__init__.py
acex/api/api/api.py
acex/api/api/routers/assets.py
acex/api/api/routers/device_configs.py
acex/api/api/routers/logical_nodes.py
acex/api/api/routers/management_connections.py
acex/api/api/routers/neds.py
acex/api/api/routers/node_instances.py
acex_api-0.1.4.dist-info/METADATA
acex_api-0.1.4.dist-info/WHEEL
acex_api-0.1.4.dist-info/RECORD
