Metadata-Version: 2.4
Name: acex-api
Version: 0.1.4
Summary: API components for acex framework
Author: Johan Lahti
Author-email: johan.lahti@acebit.se
Requires-Python: >=3.13
Classifier: Programming Language :: Python :: 3
Classifier: Programming Language :: Python :: 3.13
Classifier: Programming Language :: Python :: 3.14
Requires-Dist: acex-core
Requires-Dist: fastapi (>=0.118.0,<0.119.0)
